{
  "schema_metadata": {
    "database": "ZOOM_DATABASE",
    "schema": "ZOOM_RAW_SCHEMA",
    "extraction_timestamp": "2024-12-19",
    "total_objects": 8,
    "objects": {
      "MEETINGS": {
        "object_type": "TABLE",
        "column_count": 9,
        "columns": [
          {
            "name": "UPDATE_TIMESTAMP",
            "data_type": "TIMESTAMP_NTZ",
            "nullable": true
          },
          {
            "name": "MEETING_TOPIC",
            "data_type": "TEXT",
            "nullable": true
          },
          {
            "name": "DURATION_MINUTES",
            "data_type": "NUMBER",
            "nullable": true
          },
          {
            "name": "LOAD_TIMESTAMP",
            "data_type": "TIMESTAMP_NTZ",
            "nullable": true
          },
          {
            "name": "MEETING_ID",
            "data_type": "TEXT",
            "nullable": true
          },
          {
            "name": "SOURCE_SYSTEM",
            "data_type": "TEXT",
            "nullable": true
          },
          {
            "name": "END_TIME",
            "data_type": "TIMESTAMP_NTZ",
            "nullable": true
          },
          {
            "name": "HOST_ID",
            "data_type": "TEXT",
            "nullable": true
          },
          {
            "name": "START_TIME",
            "data_type": "TIMESTAMP_NTZ",
            "nullable": true
          }
        ]
      },
      "LICENSES": {
        "object_type": "TABLE",
        "column_count": 8,
        "columns": [
          {
            "name": "LOAD_TIMESTAMP",
            "data_type": "TIMESTAMP_NTZ",
            "nullable": true
          },
          {
            "name": "LICENSE_TYPE",
            "data_type": "TEXT",
            "nullable": true
          },
          {
            "name": "END_DATE",
            "data_type": "DATE",
            "nullable": true
          },
          {
            "name": "ASSIGNED_TO_USER_ID",
            "data_type": "TEXT",
            "nullable": true
          },
          {
            "name": "LICENSE_ID",
            "data_type": "TEXT",
            "nullable": true
          },
          {
            "name": "SOURCE_SYSTEM",
            "data_type": "TEXT",
            "nullable": true
          },
          {
            "name": "UPDATE_TIMESTAMP",
            "data_type": "TIMESTAMP_NTZ",
            "nullable": true
          },
          {
            "name": "START_DATE",
            "data_type": "DATE",
            "nullable": true
          }
        ]
      },
      "SUPPORT_TICKETS": {
        "object_type": "TABLE",
        "column_count": 8,
        "columns": [
          {
            "name": "RESOLUTION_STATUS",
            "data_type": "TEXT",
            "nullable": true
          },
          {
            "name": "UPDATE_TIMESTAMP",
            "data_type": "TIMESTAMP_NTZ",
            "nullable": true
          },
          {
            "name": "TICKET_ID",
            "data_type": "TEXT",
            "nullable": true
          },
          {
            "name": "LOAD_TIMESTAMP",
            "data_type": "TIMESTAMP_NTZ",
            "nullable": true
          },
          {
            "name": "OPEN_DATE",
            "data_type": "DATE",
            "nullable": true
          },
          {
            "name": "USER_ID",
            "data_type": "TEXT",
            "nullable": true
          },
          {
            "name": "SOURCE_SYSTEM",
            "data_type": "TEXT",
            "nullable": true
          },
          {
            "name": "TICKET_TYPE",
            "data_type": "TEXT",
            "nullable": true
          }
        ]
      },
      "USERS": {
        "object_type": "TABLE",
        "column_count": 8,
        "columns": [
          {
            "name": "EMAIL",
            "data_type": "TEXT",
            "nullable": true
          },
          {
            "name": "SOURCE_SYSTEM",
            "data_type": "TEXT",
            "nullable": true
          },
          {
            "name": "USER_NAME",
            "data_type": "TEXT",
            "nullable": true
          },
          {
            "name": "LOAD_TIMESTAMP",
            "data_type": "TIMESTAMP_NTZ",
            "nullable": true
          },
          {
            "name": "UPDATE_TIMESTAMP",
            "data_type": "TIMESTAMP_NTZ",
            "nullable": true
          },
          {
            "name": "USER_ID",
            "data_type": "TEXT",
            "nullable": true
          },
          {
            "name": "PLAN_TYPE",
            "data_type": "TEXT",
            "nullable": true
          },
          {
            "name": "COMPANY",
            "data_type": "TEXT",
            "nullable": true
          }
        ]
      },
      "BILLING_EVENTS": {
        "object_type": "TABLE",
        "column_count": 8,
        "columns": [
          {
            "name": "SOURCE_SYSTEM",
            "data_type": "TEXT",
            "nullable": true
          },
          {
            "name": "EVENT_ID",
            "data_type": "TEXT",
            "nullable": true
          },
          {
            "name": "UPDATE_TIMESTAMP",
            "data_type": "TIMESTAMP_NTZ",
            "nullable": true
          },
          {
            "name": "AMOUNT",
            "data_type": "NUMBER",
            "nullable": true
          },
          {
            "name": "EVENT_TYPE",
            "data_type": "TEXT",
            "nullable": true
          },
          {
            "name": "LOAD_TIMESTAMP",
            "data_type": "TIMESTAMP_NTZ",
            "nullable": true
          },
          {
            "name": "EVENT_DATE",
            "data_type": "DATE",
            "nullable": true
          },
          {
            "name": "USER_ID",
            "data_type": "TEXT",
            "nullable": true
          }
        ]
      },
      "PARTICIPANTS": {
        "object_type": "TABLE",
        "column_count": 8,
        "columns": [
          {
            "name": "UPDATE_TIMESTAMP",
            "data_type": "TIMESTAMP_NTZ",
            "nullable": true
          },
          {
            "name": "MEETING_ID",
            "data_type": "TEXT",
            "nullable": true
          },
          {
            "name": "SOURCE_SYSTEM",
            "data_type": "TEXT",
            "nullable": true
          },
          {
            "name": "LOAD_TIMESTAMP",
            "data_type": "TIMESTAMP_NTZ",
            "nullable": true
          },
          {
            "name": "LEAVE_TIME",
            "data_type": "TIMESTAMP_NTZ",
            "nullable": true
          },
          {
            "name": "JOIN_TIME",
            "data_type": "TIMESTAMP_NTZ",
            "nullable": true
          },
          {
            "name": "USER_ID",
            "data_type": "TEXT",
            "nullable": true
          },
          {
            "name": "PARTICIPANT_ID",
            "data_type": "TEXT",
            "nullable": true
          }
        ]
      },
      "WEBINARS": {
        "object_type": "TABLE",
        "column_count": 9,
        "columns": [
          {
            "name": "END_TIME",
            "data_type": "TIMESTAMP_NTZ",
            "nullable": true
          },
          {
            "name": "SOURCE_SYSTEM",
            "data_type": "TEXT",
            "nullable": true
          },
          {
            "name": "WEBINAR_TOPIC",
            "data_type": "TEXT",
            "nullable": true
          },
          {
            "name": "START_TIME",
            "data_type": "TIMESTAMP_NTZ",
            "nullable": true
          },
          {
            "name": "WEBINAR_ID",
            "data_type": "TEXT",
            "nullable": true
          },
          {
            "name": "LOAD_TIMESTAMP",
            "data_type": "TIMESTAMP_NTZ",
            "nullable": true
          },
          {
            "name": "REGISTRANTS",
            "data_type": "NUMBER",
            "nullable": true
          },
          {
            "name": "HOST_ID",
            "data_type": "TEXT",
            "nullable": true
          },
          {
            "name": "UPDATE_TIMESTAMP",
            "data_type": "TIMESTAMP_NTZ",
            "nullable": true
          }
        ]
      },
      "FEATURE_USAGE": {
        "object_type": "TABLE",
        "column_count": 8,
        "columns": [
          {
            "name": "FEATURE_NAME",
            "data_type": "TEXT",
            "nullable": true
          },
          {
            "name": "MEETING_ID",
            "data_type": "TEXT",
            "nullable": true
          },
          {
            "name": "USAGE_DATE",
            "data_type": "DATE",
            "nullable": true
          },
          {
            "name": "UPDATE_TIMESTAMP",
            "data_type": "TIMESTAMP_NTZ",
            "nullable": true
          },
          {
            "name": "SOURCE_SYSTEM",
            "data_type": "TEXT",
            "nullable": true
          },
          {
            "name": "USAGE_ID",
            "data_type": "TEXT",
            "nullable": true
          },
          {
            "name": "LOAD_TIMESTAMP",
            "data_type": "TIMESTAMP_NTZ",
            "nullable": true
          },
          {
            "name": "USAGE_COUNT",
            "data_type": "NUMBER",
            "nullable": true
          }
        ]
      }
    },
    "summary": {
      "tables": 8,
      "views": 0,
      "total_columns": 66,
      "data_types_used": [
        "TEXT",
        "TIMESTAMP_NTZ",
        "NUMBER",
        "DATE"
      ],
      "common_patterns": {
        "audit_columns": [
          "LOAD_TIMESTAMP",
          "UPDATE_TIMESTAMP",
          "SOURCE_SYSTEM"
        ],
        "identifier_columns": [
          "USER_ID",
          "MEETING_ID",
          "LICENSE_ID",
          "TICKET_ID",
          "EVENT_ID",
          "PARTICIPANT_ID",
          "WEBINAR_ID",
          "USAGE_ID"
        ]
      }
    }
  }
}